ClickSQL/__init__.py
ClickSQL/clickhouse/ClickHouse.py
ClickSQL/clickhouse/ClickHouseCreate.py
ClickSQL/clickhouse/ClickHouseExt.py
ClickSQL/clickhouse/__init__.py
ClickSQL/conf/__init__.py
ClickSQL/errors/__init__.py
ClickSQL/func/__init__.py
ClickSQL/func/dump.py
ClickSQL/nodes/__init__.py
ClickSQL/nodes/base.py
ClickSQL/nodes/groupby.py
ClickSQL/nodes/merge.py
ClickSQL/pool/__init__.py
ClickSQL/pool/pooled_ch.py
ClickSQL/utils/__init__.py
ClickSQL/utils/boost_up.py
ClickSQL/utils/cached_property.py
ClickSQL/utils/chunk.py
ClickSQL/utils/file_cache.py
ClickSQL/utils/lazy_load.py
ClickSQL/utils/o_server.py
ClickSQL/utils/parse_rfc_1738_args.py
ClickSQL/utils/process_bar.py
ClickSQL/utils/singleton.py
ClickSQL/utils/uuid_generator.py
test/__init__.py
test/conn.py
test/test_ClickHouseExt.py
test/test_ClickHouseInsert.py
test/test_Clickhouse.py
test/test_ClickhouseCreate.py
test/test_configs.py
test/test_delay_function.py
test/test_multiple_value_for_argumen_transfer_sql_format.py
test/factor_test/__init__.py
test/factor_test/test_prepare.py
ClickSQL-0.1.9.4.dist-info/LICENSE
ClickSQL-0.1.9.4.dist-info/METADATA
ClickSQL-0.1.9.4.dist-info/WHEEL
ClickSQL-0.1.9.4.dist-info/top_level.txt
ClickSQL-0.1.9.4.dist-info/RECORD
