Metadata-Version: 2.1
Name: ClickSQL
Version: 0.1.9.4
Summary: A python client for Clickhouse
Home-page: http://www.github.com/sn0wfree/ClickSQL
Author: sn0wfree
Author-email: snowfreedom0815@gmail.com
License: MIT Licence
Keywords: ClickHouse,Databases,SQL,Python,Client
Platform: UNKNOWN
